{"nodes":[{"id":"node0","data":{"message":"INIT"},"next":{"type":"conditional","data":[{"next":"node1","condition":"HAS_CROPS_READY"},{"next":"node2","condition":"ELSE"}]}},{"id":"node1","data":{"textID":"standardAttack","message":"LAUNCH_CROPS","animData":[[0,2],[0,2],[0,3],[0,0,true]]}},{"id":"node2","data":{},"next":{"type":"conditional","data":[{"next":"node3","weight":"0.6"},{"next":"node4","weight":"0.3"},{"next":"node6","weight":"0.1"}],"condition":"random"}},{"id":"node3","data":{"textID":"fileBPermit","message":"TRY_PLANT_CROP","action":"bpermit","animData":[[0,4],[0,5]]},"next":{"type":"conditional","data":[{"next":"node5","condition":"SUCCESS"},{"next":"node4","condition":"ELSE"}]}},{"id":"node4","data":{"textID":"standardAttack","message":"WEAK_ATTACK","animData":[[0,2],[0,2],[0,3],[0,0,true]]}},{"id":"node5","data":{"message":"END"}},{"id":"node6","data":{"textID":"buildHouse","message":"TRY_PLANT_CROP","action":"house","animData":[[0,4],[0,5]]},"next":{"type":"conditional","data":[{"next":"node5","condition":"SUCCESS"},{"next":"node3","condition":"ELSE"}]}}]}